pyvesc_fix/__init__.py
pyvesc_fix/__main__.py
pyvesc_fix/VESC/VESC.py
pyvesc_fix/VESC/__init__.py
pyvesc_fix/VESC/messages/Vedder_BLDC_Commands.py
pyvesc_fix/VESC/messages/__init__.py
pyvesc_fix/VESC/messages/getters.py
pyvesc_fix/VESC/messages/setters.py
pyvesc_fix/protocol/__init__.py
pyvesc_fix/protocol/base.py
pyvesc_fix/protocol/interface.py
pyvesc_fix/protocol/packet/__init__.py
pyvesc_fix/protocol/packet/codec.py
pyvesc_fix/protocol/packet/exceptions.py
pyvesc_fix/protocol/packet/structure.py
tests/__init__.py
tests/test_vesc.py
pyvesc_fix-1.0.3.dist-info/LICENSE.txt
pyvesc_fix-1.0.3.dist-info/METADATA
pyvesc_fix-1.0.3.dist-info/WHEEL
pyvesc_fix-1.0.3.dist-info/top_level.txt
pyvesc_fix-1.0.3.dist-info/RECORD
