Metadata-Version: 2.1
Name: pyvesc_fix
Version: 1.0.3
Summary: This is a repackagin of a fork from the pyvesc library.
Home-page: https://github.com/Hanra-s-work/PyVESC
Download-URL: https://github.com/Hanra-s-work/PyVESC1.0.3
Author: Henry Letellier
Author-email: henrysoftwarehouse@protonmail.com
Keywords: vesc,VESC,communication,protocol,packet
Classifier: Programming Language :: Python :: 3
Classifier: Operating System :: OS Independent
License-File: LICENSE.txt
Requires-Dist: pyserial ==3.5
Requires-Dist: crccheck >=0.6
Requires-Dist: pythoncrc ==1.21
